{
  "products": [
    {
      "id": 1,
      "image": "https://happilyunprocessed.com/wp-content/uploads/2022/11/Juiciest-Burger-Youll-Ever-eat-2.jpg",
      "title": "Delicious Burger",
      "price": 8.99,
      "description": "A mouth-watering burger with juicy beef patty, cheese, and fresh veggies."
    },
    {
      "id": 2,
      "image": "https://www.homemaderecipesfromscratch.com/wp-content/uploads/2020/05/spaghetti-bolognese-1-official.webp",
      "title": "Spaghetti Bolognese",
      "price": 12.99,
      "description": "Classic Italian spaghetti with rich meat sauce and grated Parmesan cheese."
    },
    {
      "id": 3,
      "image": "https://thewoodenskillet.com/wp-content/uploads/2021/08/grilled-chicken-caesar-salad-recipe-1.jpg",
      "title": "Chicken Caesar Salad",
      "price": 10.49,
      "description": "Fresh romaine lettuce, grilled chicken, croutons, and Caesar dressing."
    },
    {
      "id": 4,
      "image": "https://www.easyanddelish.com/wp-content/uploads/2020/05/Best-Homemade-Margherita-pizza-featured-image.jpg",
      "title": "Margherita Pizza",
      "price": 9.5,
      "description": "Traditional Italian pizza with tomato sauce, mozzarella, and fresh basil."
    },
    {
      "id": 5,
      "image": "https://tokyousushi.ie/wp-content/uploads/2020/11/Large-Sushi-Platter.jpg",
      "title": "Sushi Platter",
      "price": 15.99,
      "description": "Assorted sushi rolls with fresh fish, avocado, and soy sauce."
    },
    {
      "id": 6,
      "image": "https://www.kitchensanctuary.com/wp-content/uploads/2019/09/Chicken-Tikka-Masala-square-FS-51.jpg",
      "title": "Chicken Tikka Masala",
      "price": 11.99,
      "description": "Indian spiced grilled chicken in a creamy tomato-based sauce."
    },
    {
      "id": 7,
      "image": "https://encrypted-tbn0.gstatic.com/images?q=tbn:ANd9GcR12f-O3NhOf709m3tatqDm4_SmfkgZqweH2FpFqleS_7rU4rYXkHQNKKrKvsncC5yefBA&usqp=CAU",
      "title": "Caesar Wrap",
      "price": 7.99,
      "description": "Grilled chicken, romaine lettuce, Parmesan cheese, and Caesar dressing in a wrap."
    },
    {
      "id": 8,
      "image": "https://files.ketodietapp.com/Blog/files/2021/05/keto-fish-and-chips-5.jpg",
      "title": "Fish and Chips",
      "price": 13.49,
      "description": "Crispy battered fish fillets with French fries and tartar sauce."
    },
    {
      "id": 9,
      "image": "https://encrypted-tbn0.gstatic.com/images?q=tbn:ANd9GcSgwpUmwq6fnGvkCAUNCRj0tZWeydJP2HL82A&usqp=CAU",
      "title": "Caprese Salad",
      "price": 9.99,
      "description": "Fresh mozzarella cheese, tomatoes, basil, and balsamic glaze."
    },
    {
      "id": 10,
      "image": "https://img.taste.com.au/R_dRdL7V/taste/2022/09/healthy-tacos-recipe-181113-1.jpg",
      "title": "Beef Tacos",
      "price": 8.99,
      "description": "Soft tortillas filled with seasoned beef, lettuce, cheese, and salsa."
    },
    {
      "id": 11,
      "image": "https://avegtastefromatoz.com/wp-content/uploads/2018/10/miso-soup-FIWP.jpg",
      "title": "Miso Soup",
      "price": 4.99,
      "description": "Traditional Japanese soup made with soybean paste, tofu, and seaweed."
    },
    {
      "id": 12,
      "image": "https://www.jocooks.com/wp-content/uploads/2018/11/oven-roasted-chicken-shawarma-1-2-500x375.jpg",
      "title": "Chicken Shawarma",
      "price": 10.99,
      "description": "Grilled marinated chicken, garlic sauce, and vegetables wrapped in pita bread."
    },
    {
      "id": 13,
      "image": "https://hips.hearstapps.com/hmg-prod/images/greek-salad-index-642f292397bbf.jpg?crop=0.502xw:1.00xh;0.250xw,0&resize=1200:*",
      "title": "Greek Salad",
      "price": 8.49,
      "description": "Fresh cucumbers, tomatoes, olives, feta cheese, and Greek dressing."
    },
    {
      "id": 14,
      "image": "https://www.deliciousmagazine.co.uk/wp-content/uploads/2020/06/beef-burrito-bowls.jpg",
      "title": "Beef Burrito",
      "price": 9.99,
      "description": "Large flour tortilla filled with seasoned beef, rice, beans, and toppings."
    },
    {
      "id": 15,
      "image": "https://insanelygoodrecipes.com/wp-content/uploads/2022/09/Homemade-Nutella-Stuffed-Pancake-with-Fresh-Strawberries-500x375.jpg",
      "title": "Pancakes",
      "price": 7.49,
      "description": "Fluffy pancakes served with butter, maple syrup, and fresh berries."
    },
    {
      "id": 16,
      "image": "https://www.thecountrycook.net/wp-content/uploads/2021/03/Veggie-Pizza.jpg",
      "title": "Veggie Pizza",
      "price": 10.99,
      "description": "Pizza topped with assorted vegetables, tomato sauce, and melted cheese."
    },
    {
      "id": 17,
      "image": "https://khinskitchen.com/wp-content/uploads/2023/03/beef-stir-fry-01.jpg",
      "title": "Beef Stir Fry",
      "price": 11.49,
      "description": "Sliced beef, mixed vegetables, and soy-based sauce served over rice."
    },
    {
      "id": 18,
      "image": "https://theyummybowl.com/wp-content/uploads/VEGETARIAN-PIZZA-GF-REC-500x500.jpg",
      "title": "Cheeseburger",
      "price": 9.99,
      "description": "Classic cheeseburger with beef patty, cheese, lettuce, and pickles."
    },
    {
      "id": 19,
      "image": "https://storcpdkenticomedia.blob.core.windows.net/media/recipemanagementsystem/media/recipe-media-files/recipes/retail/x17/19134-margherita-pasta-760x580.jpg?ext=.jpg",
      "title": "Margherita Pasta",
      "price": 10.99,
      "description": "Penne pasta tossed in tomato sauce, mozzarella cheese, and fresh basil."
    },
    {
      "id": 20,
      "image": "https://twoplaidaprons.com/wp-content/uploads/2023/04/Thai-fried-rice-with-sliced-cucumbers-thumbnaill-photo.jpg",
      "title": "Fried Rice",
      "price": 8.49,
      "description": "Stir-fried rice with eggs, vegetables, and choice of chicken, beef, or shrimp."
    },
    {
      "id": 21,
      "image": "https://happilyunprocessed.com/wp-content/uploads/2022/11/Juiciest-Burger-Youll-Ever-eat-2.jpg",
      "title": "Delicious Burger",
      "price": 8.99,
      "description": "A mouth-watering burger with juicy beef patty, cheese, and fresh veggies."
    },
    {
      "id": 22,
      "image": "https://www.homemaderecipesfromscratch.com/wp-content/uploads/2020/05/spaghetti-bolognese-1-official.webp",
      "title": "Spaghetti Bolognese",
      "price": 12.99,
      "description": "Classic Italian spaghetti with rich meat sauce and grated Parmesan cheese."
    },
    {
      "id": 23,
      "image": "https://thewoodenskillet.com/wp-content/uploads/2021/08/grilled-chicken-caesar-salad-recipe-1.jpg",
      "title": "Chicken Caesar Salad",
      "price": 10.49,
      "description": "Fresh romaine lettuce, grilled chicken, croutons, and Caesar dressing."
    },
    {
      "id": 24,
      "image": "https://www.easyanddelish.com/wp-content/uploads/2020/05/Best-Homemade-Margherita-pizza-featured-image.jpg",
      "title": "Margherita Pizza",
      "price": 9.5,
      "description": "Traditional Italian pizza with tomato sauce, mozzarella, and fresh basil."
    },
    {
      "id": 25,
      "image": "https://img.taste.com.au/R_dRdL7V/taste/2022/09/healthy-tacos-recipe-181113-1.jpg",
      "title": "Beef Tacos",
      "price": 8.99,
      "description": "Soft tortillas filled with seasoned beef, lettuce, cheese, and salsa."
    },
    {
      "id": 26,
      "image": "https://avegtastefromatoz.com/wp-content/uploads/2018/10/miso-soup-FIWP.jpg",
      "title": "Miso Soup",
      "price": 4.99,
      "description": "Traditional Japanese soup made with soybean paste, tofu, and seaweed."
    },
    {
      "id": 27,
      "image": "https://www.jocooks.com/wp-content/uploads/2018/11/oven-roasted-chicken-shawarma-1-2-500x375.jpg",
      "title": "Chicken Shawarma",
      "price": 10.99,
      "description": "Grilled marinated chicken, garlic sauce, and vegetables wrapped in pita bread."
    },
    {
      "id": 28,
      "image": "https://hips.hearstapps.com/hmg-prod/images/greek-salad-index-642f292397bbf.jpg?crop=0.502xw:1.00xh;0.250xw,0&resize=1200:*",
      "title": "Greek Salad",
      "price": 8.49,
      "description": "Fresh cucumbers, tomatoes, olives, feta cheese, and Greek dressing."
    },
    {
      "id": 29,
      "image": "https://www.deliciousmagazine.co.uk/wp-content/uploads/2020/06/beef-burrito-bowls.jpg",
      "title": "Beef Burrito",
      "price": 9.99,
      "description": "Large flour tortilla filled with seasoned beef, rice, beans, and toppings."
    },
    {
      "id": 30,
      "image": "https://insanelygoodrecipes.com/wp-content/uploads/2022/09/Homemade-Nutella-Stuffed-Pancake-with-Fresh-Strawberries-500x375.jpg",
      "title": "Pancakes",
      "price": 7.49,
      "description": "Fluffy pancakes served with butter, maple syrup, and fresh berries."
    },
    {
      "id": 31,
      "image": "https://www.thecountrycook.net/wp-content/uploads/2021/03/Veggie-Pizza.jpg",
      "title": "Veggie Pizza",
      "price": 10.99,
      "description": "Pizza topped with assorted vegetables, tomato sauce, and melted cheese."
    },
    {
      "id": 32,
      "image": "https://khinskitchen.com/wp-content/uploads/2023/03/beef-stir-fry-01.jpg",
      "title": "Beef Stir Fry",
      "price": 11.49,
      "description": "Sliced beef, mixed vegetables, and soy-based sauce served over rice."
    }
  ],
  "users": [
    {
      "name": "mods",
      "email": "moath.f.alkhouly@gmail.com",
      "password": "12345678",
      "repetpassword": "12345678",
      "id": 1
    },
    {
      "name": "mods",
      "email": "moath.f.alkhouly@gmail.com",
      "password": "12345678",
      "repetpassword": "12345678",
      "id": 2
    },
    {
      "name": "mods",
      "email": "moath.f.alkhouly@gmail.com",
      "password": "12345678",
      "repetpassword": "12345678",
      "id": 3
    },
    {
      "id": 4
    },
    {
      "name": "edcf",
      "email": "moath.f.alkhuy@gmail.com",
      "password": "12345678",
      "repetpassword": "12345678",
      "id": 5
    },
    {
      "name": "edcf",
      "email": "moath.f.alkhuy@gmail.com",
      "password": "12345678",
      "repetpassword": "12345678",
      "id": 6
    },
    {
      "name": "edcf",
      "email": "moath.f.alkhuy@gmail.com",
      "password": "12345678",
      "repetpassword": "12345678",
      "id": 7
    },
    {
      "name": "newspaper",
      "email": "a@m",
      "password": "12345678",
      "repetpassword": "12345678",
      "id": 8
    },
    {
      "name": "newspaper",
      "email": "m@q",
      "password": "12345678",
      "repetpassword": "12345678",
      "id": 9
    },
    {
      "name": "hanen",
      "email": "aaa@ee",
      "password": "12345678",
      "repetpassword": "12345678",
      "id": 10
    }
  ],
  "Posts": [
    {
      "Name": "faten",
      "post": "goood",
      "image1": "https://cloudflare-ipfs.com/ipfs/Qmd3W5DuhgHirLHGVixi6V76LhCkZUz6pnFt5AJBiyvHye/avatar/275.jpg",
      "comments": [
        {
          "img": "https://avatars.githubusercontent.com/u/77556501",
          "text": "like",
          "date": "7/4/2023, 8:54:12 AM"
        },
        {
          "img": "https://avatars.githubusercontent.com/u/55070362",
          "text": "like1",
          "date": "7/4/2023, 8:54:18 AM"
        },
        {
          "img": "https://cloudflare-ipfs.com/ipfs/Qmd3W5DuhgHirLHGVixi6V76LhCkZUz6pnFt5AJBiyvHye/avatar/1191.jpg",
          "text": "ooo",
          "date": "7/4/2023, 11:08:48 AM"
        }
      ],
      "id": 1
    },
    {
      "Name": "omer",
      "post": "like",
      "image1": "https://cloudflare-ipfs.com/ipfs/Qmd3W5DuhgHirLHGVixi6V76LhCkZUz6pnFt5AJBiyvHye/avatar/1137.jpg",
      "comments": [],
      "id": 2
    },
    {
      "Name": "moath",
      "post": "new",
      "image1": "https://avatars.githubusercontent.com/u/69563219",
      "comments": [
        {
          "img": "https://cloudflare-ipfs.com/ipfs/Qmd3W5DuhgHirLHGVixi6V76LhCkZUz6pnFt5AJBiyvHye/avatar/799.jpg",
          "text": "hhhhhhhh",
          "date": "7/4/2023, 11:53:43 AM"
        },
        {
          "img": "https://avatars.githubusercontent.com/u/95344862",
          "text": "kkkkkkkkk",
          "date": "7/4/2023, 11:54:00 AM"
        },
        {
          "img": "https://cloudflare-ipfs.com/ipfs/Qmd3W5DuhgHirLHGVixi6V76LhCkZUz6pnFt5AJBiyvHye/avatar/1212.jpg",
          "text": "ggggggggg",
          "date": "7/4/2023, 12:38:49 PM"
        }
      ],
      "id": 3
    }
  ]
}